gitcloak/__init__.py
gitcloak/app.py
gitcloak/assets/css/style.css
gitcloak/assets/dist/css/bootstrap.min.css
gitcloak/assets/dist/icons/LICENSE
gitcloak/assets/dist/icons/file.svg
gitcloak/assets/dist/icons/folder.svg
gitcloak/classes/__init__.py
gitcloak/classes/git.py
gitcloak/classes/markdown.py
gitcloak/templates/base.html
gitcloak/templates/index.html
gitcloak/templates/path.html
gitcloak/templates/preview.html
gitcloak-0.0.6.dist-info/METADATA
gitcloak-0.0.6.dist-info/WHEEL
gitcloak-0.0.6.dist-info/entry_points.txt
gitcloak-0.0.6.dist-info/licenses/LICENSE
gitcloak-0.0.6.dist-info/RECORD
