Metadata-Version: 2.3
Name: gitcloak
Version: 0.0.6
Summary: Simple Python-based private frontend for GitHub repositories
Project-URL: Homepage, https://git.private.coffee/PrivateCoffee/gitcloak
Project-URL: Bug Tracker, https://git.private.coffee/PrivateCoffee/gitcloak/issues
Author-email: "Private.coffee Team" <support@private.coffee>
License: Copyright (c) 2024 Private.coffee Team <support@private.coffee>
License-File: LICENSE
Classifier: License :: OSI Approved :: MIT License
Classifier: Operating System :: OS Independent
Classifier: Programming Language :: Python :: 3
Requires-Python: >=3.10
Requires-Dist: dulwich
Requires-Dist: flask
Requires-Dist: markdown2[all]
Requires-Dist: requests
